{"word":"chanced","rank":5048,"occurrence":0.0012036,"records":[{"word":"chanced","phonetic":"/ˈt͡ʃɑːnst/","phonetics":[{"text":"/ˈt͡ʃɑːnst/","audio":""},{"text":"/ˈt͡ʃeənst/","audio":""}],"meanings":[{"partOfSpeech":"verb","definitions":[{"definition":"To happen by chance, to occur.","synonyms":[],"antonyms":[],"example":"It chanced that I found a solution the very next day."},{"definition":"To befall; to happen to.","synonyms":[],"antonyms":[]},{"definition":"To try or risk.","synonyms":[],"antonyms":[],"example":"Shall we carry the umbrella, or chance a rainstorm?"},{"definition":"To discover something by chance.","synonyms":[],"antonyms":[],"example":"He chanced upon a kindly stranger who showed him the way."},{"definition":"(Belize) To rob, cheat or swindle someone.","synonyms":[],"antonyms":[],"example":"The car broke down a week after I bought it. I was chanced by that fast-talking salesman."}],"synonyms":["come across","come on","come upon","encounter","stumble upon","come to pass","occur","transpire","deceive","fool","trick","test"],"antonyms":[]}],"license":{"name":"CC BY-SA 3.0","url":"https://creativecommons.org/licenses/by-sa/3.0"},"sourceUrls":["https://en.wiktionary.org/wiki/chance","https://en.wiktionary.org/wiki/chanced"]}]}