{"word":"battleship","rank":15979,"occurrence":0.0000837,"records":[{"word":"battleship","phonetics":[],"meanings":[{"partOfSpeech":"noun","definitions":[{"definition":"Large capital warship displacing tens of thousands of tons, heavily armoured and armed with big guns. Battleships are now obsolescent, replaced by smaller vessels with guided missiles. Types: dreadnought, pre-dreadnought.","synonyms":[],"antonyms":[]},{"definition":"Non-functional rocket stage, used for configuration and integration tests.","synonyms":[],"antonyms":[]},{"definition":"A guessing game played on grid paper, see Battleship (game)","synonyms":[],"antonyms":[]}],"synonyms":[],"antonyms":[]}],"license":{"name":"CC BY-SA 3.0","url":"https://creativecommons.org/licenses/by-sa/3.0"},"sourceUrls":["https://en.wiktionary.org/wiki/battleship"]}]}