{"word":"earthen","rank":9809,"occurrence":0.0003399,"records":[{"word":"earthen","phonetic":"/ˈɜː(ɹ)θən/","phonetics":[{"text":"/ˈɜː(ɹ)θən/","audio":""},{"text":"/ˈəɹθən/","audio":""}],"meanings":[{"partOfSpeech":"adjective","definitions":[{"definition":"Made of earth or mud.","synonyms":[],"antonyms":[]},{"definition":"Made of clay (especially said of pottery).","synonyms":[],"antonyms":[]},{"definition":"Earthly.","synonyms":[],"antonyms":[]}],"synonyms":[],"antonyms":[]}],"license":{"name":"CC BY-SA 3.0","url":"https://creativecommons.org/licenses/by-sa/3.0"},"sourceUrls":["https://en.wiktionary.org/wiki/earthen"]},{"word":"earthen","phonetic":"/ˈɜː(ɹ)θən/","phonetics":[{"text":"/ˈɜː(ɹ)θən/","audio":""},{"text":"/ˈəɹθən/","audio":""}],"meanings":[{"partOfSpeech":"verb","definitions":[{"definition":"To provide or add soil to","synonyms":[],"antonyms":[]},{"definition":"To make earthly or earthlike","synonyms":[],"antonyms":[]}],"synonyms":[],"antonyms":[]}],"license":{"name":"CC BY-SA 3.0","url":"https://creativecommons.org/licenses/by-sa/3.0"},"sourceUrls":["https://en.wiktionary.org/wiki/earthen"]}]}