{"word":"exceedingly","rank":2525,"occurrence":0.0029445,"records":[{"word":"exceedingly","phonetic":"/ɪkˈsiːdɪŋli/","phonetics":[{"text":"/ɪkˈsiːdɪŋli/","audio":"https://api.dictionaryapi.dev/media/pronunciations/en/exceedingly-us.mp3","sourceUrl":"https://commons.wikimedia.org/w/index.php?curid=1749833","license":{"name":"BY-SA 3.0","url":"https://creativecommons.org/licenses/by-sa/3.0"}}],"meanings":[{"partOfSpeech":"adverb","definitions":[{"definition":"To a great or unusual degree, extent, etc.; extremely","synonyms":[],"antonyms":[]}],"synonyms":[],"antonyms":[]}],"license":{"name":"CC BY-SA 3.0","url":"https://creativecommons.org/licenses/by-sa/3.0"},"sourceUrls":["https://en.wiktionary.org/wiki/exceedingly"]}]}