{"word":"exclusively","rank":5126,"occurrence":0.0011788,"records":[{"word":"exclusively","phonetic":"/ɪkˈskluːsɪvli/","phonetics":[{"text":"/ɪkˈskluːsɪvli/","audio":""}],"meanings":[{"partOfSpeech":"adverb","definitions":[{"definition":"(focus) to the exclusion of anything or anyone else; solely or entirely","synonyms":[],"antonyms":[]}],"synonyms":["alone","exclusively"],"antonyms":[]}],"license":{"name":"CC BY-SA 3.0","url":"https://creativecommons.org/licenses/by-sa/3.0"},"sourceUrls":["https://en.wiktionary.org/wiki/exclusively"]}]}