{"word":"dapper","rank":15899,"occurrence":0.0000854,"records":[{"word":"dapper","phonetic":"/ˈdæpə(ɹ)/","phonetics":[{"text":"/ˈdæpə(ɹ)/","audio":""}],"meanings":[{"partOfSpeech":"adjective","definitions":[{"definition":"Neat, trim.","synonyms":[],"antonyms":[]},{"definition":"Stylishly dressed, neatly dressed, spiffy.","synonyms":[],"antonyms":[]},{"definition":"Quick; little and active.","synonyms":[],"antonyms":[]}],"synonyms":[],"antonyms":[]}],"license":{"name":"CC BY-SA 3.0","url":"https://creativecommons.org/licenses/by-sa/3.0"},"sourceUrls":["https://en.wiktionary.org/wiki/dapper"]}]}