{"word":"pander","rank":18176,"occurrence":0.0000515,"records":[{"word":"pander","phonetics":[{"audio":"https://api.dictionaryapi.dev/media/pronunciations/en/pander-au.mp3","sourceUrl":"https://commons.wikimedia.org/w/index.php?curid=75833663","license":{"name":"BY-SA 4.0","url":"https://creativecommons.org/licenses/by-sa/4.0"}},{"text":"/ˈpændə/","audio":""},{"text":"/ˈpændɚ/","audio":"https://api.dictionaryapi.dev/media/pronunciations/en/pander-us.mp3","sourceUrl":"https://commons.wikimedia.org/w/index.php?curid=268415"}],"meanings":[{"partOfSpeech":"noun","definitions":[{"definition":"A person who furthers the illicit love-affairs of others; a pimp or procurer.","synonyms":["panderer"],"antonyms":[]},{"definition":"An offer of illicit sex with a third party.","synonyms":[],"antonyms":[]},{"definition":"An illicit or illegal offer, usually to tempt.","synonyms":[],"antonyms":[]},{"definition":"(by extension) One who ministers to the evil designs and passions of another.","synonyms":[],"antonyms":[]}],"synonyms":["panderer"],"antonyms":[]},{"partOfSpeech":"verb","definitions":[{"definition":"To tempt with, to appeal or cater to (improper motivations, etc.); to assist in gratification.","synonyms":[],"antonyms":[],"example":"His latest speech panders to the worst instincts of the electorate."},{"definition":"To offer illicit sex with a third party; to pimp.","synonyms":[],"antonyms":[]},{"definition":"To act as a pander for (somebody).","synonyms":[],"antonyms":[]}],"synonyms":["hustle","prostitute","whore out"],"antonyms":[]}],"license":{"name":"CC BY-SA 3.0","url":"https://creativecommons.org/licenses/by-sa/3.0"},"sourceUrls":["https://en.wiktionary.org/wiki/pander"]}]}