{"word":"happy","rank":493,"occurrence":0.0162105,"records":[{"word":"happy","phonetics":[{"audio":"https://api.dictionaryapi.dev/media/pronunciations/en/happy-au.mp3","sourceUrl":"https://commons.wikimedia.org/w/index.php?curid=75797241","license":{"name":"BY-SA 4.0","url":"https://creativecommons.org/licenses/by-sa/4.0"}},{"text":"/ˈhæpiː/","audio":"https://api.dictionaryapi.dev/media/pronunciations/en/happy-uk.mp3","sourceUrl":"https://commons.wikimedia.org/w/index.php?curid=9021973","license":{"name":"BY 3.0 US","url":"https://creativecommons.org/licenses/by/3.0/us"}},{"text":"/ˈhæpi/","audio":"https://api.dictionaryapi.dev/media/pronunciations/en/happy-us.mp3","sourceUrl":"https://commons.wikimedia.org/w/index.php?curid=545617","license":{"name":"BY-SA 3.0","url":"https://creativecommons.org/licenses/by-sa/3.0"}}],"meanings":[{"partOfSpeech":"noun","definitions":[{"definition":"A happy event, thing, person, etc.","synonyms":[],"antonyms":[]}],"synonyms":[],"antonyms":[]},{"partOfSpeech":"noun","definitions":[{"definition":"Preceded by the: happy people as a group.","synonyms":[],"antonyms":[]}],"synonyms":[],"antonyms":[]},{"partOfSpeech":"verb","definitions":[{"definition":"Often followed by up: to become happy; to brighten up, to cheer up.","synonyms":[],"antonyms":[]},{"definition":"Often followed by up: to make happy; to brighten, to cheer, to enliven.","synonyms":[],"antonyms":[]}],"synonyms":["happify"],"antonyms":[]},{"partOfSpeech":"adjective","definitions":[{"definition":"Having a feeling arising from a consciousness of well-being or of enjoyment; enjoying good of any kind, such as comfort, peace, or tranquillity; blissful, contented, joyous.","synonyms":[],"antonyms":[],"example":"Music makes me feel happy."},{"definition":"Experiencing the effect of favourable fortune; favored by fortune or luck; fortunate, lucky, propitious.","synonyms":[],"antonyms":[]},{"definition":"Content, satisfied (with or to do something); having no objection (to something).","synonyms":[],"antonyms":[],"example":"Are you happy to pay me back by the end of the week?"},{"definition":"(Of acts, speech, etc.) Appropriate, apt, felicitous.","synonyms":[],"antonyms":[],"example":"a happy coincidence"},{"definition":"(in combination) Favoring or inclined to use.","synonyms":[],"antonyms":[],"example":"slaphappy, trigger-happy"},{"definition":"(of people, often followed by \"at\" or \"in\") Dexterous, ready, skilful.","synonyms":[],"antonyms":[]}],"synonyms":["cheerful","content","delighted","elated","exultant","glad","joyful","jubilant","merry","orgasmic","fortunate","lucky","propitious"],"antonyms":["inappropriate","inapt","unfelicitous","disenchanted","dissatisfied","blue","depressed","down","miserable","moody","morose","sad","unhappy","unfortunate","unlucky","unpropitious"]}],"license":{"name":"CC BY-SA 3.0","url":"https://creativecommons.org/licenses/by-sa/3.0"},"sourceUrls":["https://en.wiktionary.org/wiki/happy"]}]}