{"word":"pascal","rank":11800,"occurrence":0.0002088,"records":[{"word":"pascal","phonetic":"/ˈpæskl̩/","phonetics":[{"text":"/ˈpæskl̩/","audio":""},{"text":"/pæsˈkæl/","audio":""}],"meanings":[{"partOfSpeech":"noun","definitions":[{"definition":"In the International System of Units, the derived unit of pressure and stress; one newton per square metre. Symbol: Pa.","synonyms":[],"antonyms":[]}],"synonyms":[],"antonyms":[]}],"license":{"name":"CC BY-SA 3.0","url":"https://creativecommons.org/licenses/by-sa/3.0"},"sourceUrls":["https://en.wiktionary.org/wiki/pascal"]}]}