{"word":"amazing","rank":5876,"occurrence":0.0009595,"records":[{"word":"amazing","phonetic":"/əˈmeɪzɪŋ/","phonetics":[{"text":"/əˈmeɪzɪŋ/","audio":""},{"text":"/əˈmeɪzɪŋ/","audio":"https://api.dictionaryapi.dev/media/pronunciations/en/amazing-us.mp3","sourceUrl":"https://commons.wikimedia.org/w/index.php?curid=1230794","license":{"name":"BY-SA 3.0","url":"https://creativecommons.org/licenses/by-sa/3.0"}}],"meanings":[{"partOfSpeech":"verb","definitions":[{"definition":"To fill with wonder and surprise; to astonish, astound, surprise or perplex.","synonyms":[],"antonyms":[],"example":"He was amazed when he found that the girl was a robot."},{"definition":"To undergo amazement; to be astounded.","synonyms":[],"antonyms":[]},{"definition":"To stupefy; to knock unconscious.","synonyms":[],"antonyms":[]},{"definition":"To bewilder; to stupefy; to bring into a maze.","synonyms":[],"antonyms":[]},{"definition":"To terrify, to fill with panic.","synonyms":[],"antonyms":[]}],"synonyms":[],"antonyms":[]},{"partOfSpeech":"adjective","definitions":[{"definition":"Causing wonder and amazement; very surprising.","synonyms":[],"antonyms":[]},{"definition":"Possessing uniquely wonderful qualities.","synonyms":[],"antonyms":[]},{"definition":"Very good.","synonyms":[],"antonyms":[],"example":"2015, June 10, Lindsey Bever, \"Morning Mix: Another reason seeing-eye dogs are amazing\"http//www.washingtonpost.com/news/morning-mix/wp/2015/06/10/another-heroic-story-showing-why-seeing-eye-dogs-are-amazing/"}],"synonyms":[],"antonyms":[]}],"license":{"name":"CC BY-SA 3.0","url":"https://creativecommons.org/licenses/by-sa/3.0"},"sourceUrls":["https://en.wiktionary.org/wiki/amaze","https://en.wiktionary.org/wiki/amazing"]}]}