{"word":"glow","rank":3230,"occurrence":0.0021707,"records":[{"word":"glow","phonetic":"/ɡləʊ/","phonetics":[{"text":"/ɡləʊ/","audio":""},{"text":"/ɡloʊ/","audio":"https://api.dictionaryapi.dev/media/pronunciations/en/glow-us.mp3","sourceUrl":"https://commons.wikimedia.org/w/index.php?curid=2100748","license":{"name":"BY-SA 3.0","url":"https://creativecommons.org/licenses/by-sa/3.0"}}],"meanings":[{"partOfSpeech":"noun","definitions":[{"definition":"The state of a glowing object.","synonyms":[],"antonyms":[]},{"definition":"The condition of being passionate or having warm feelings.","synonyms":[],"antonyms":[]},{"definition":"The brilliance or warmth of color in an environment or on a person (especially one's face).","synonyms":[],"antonyms":[],"example":"He had a bright red glow on his face."}],"synonyms":[],"antonyms":[]},{"partOfSpeech":"verb","definitions":[{"definition":"To give off light from heat or to emit light as if heated.","synonyms":[],"antonyms":[],"example":"The fire was still glowing after ten hours."},{"definition":"To radiate some emotional quality like light.","synonyms":[],"antonyms":[],"example":"The zealots glowed with religious fervor."},{"definition":"To gaze especially passionately at something.","synonyms":[],"antonyms":[]},{"definition":"To radiate thermal heat.","synonyms":[],"antonyms":[],"example":"After their workout, the gymnasts' faces were glowing red."},{"definition":"To shine brightly and steadily.","synonyms":[],"antonyms":[],"example":"The new baby's room glows with bright, loving colors."},{"definition":"To make hot; to flush.","synonyms":[],"antonyms":[]},{"definition":"To feel hot; to have a burning sensation, as of the skin, from friction, exercise, etc.; to burn.","synonyms":[],"antonyms":[]}],"synonyms":[],"antonyms":[]}],"license":{"name":"CC BY-SA 3.0","url":"https://creativecommons.org/licenses/by-sa/3.0"},"sourceUrls":["https://en.wiktionary.org/wiki/glow"]}]}