{"word":"ye","rank":442,"occurrence":0.0182978,"records":[{"word":"ye","phonetic":"/jiː/","phonetics":[{"text":"/jiː/","audio":""},{"text":"/jiː/","audio":"https://api.dictionaryapi.dev/media/pronunciations/en/ye-1-us.mp3","sourceUrl":"https://commons.wikimedia.org/w/index.php?curid=867668","license":{"name":"BY-SA 3.0","url":"https://creativecommons.org/licenses/by-sa/3.0"}}],"meanings":[{"partOfSpeech":"verb","definitions":[{"definition":"Address a single person by the use of the pronoun ye instead of thou.","synonyms":[],"antonyms":[]}],"synonyms":["yeet"],"antonyms":["thou"]},{"partOfSpeech":"pronoun","definitions":[{"definition":"(obsolete outside Northern England) You (the people being addressed).","synonyms":[],"antonyms":[]},{"definition":"You, refers to one person addressed.","synonyms":[],"antonyms":[]}],"synonyms":[],"antonyms":[]}],"license":{"name":"CC BY-SA 3.0","url":"https://creativecommons.org/licenses/by-sa/3.0"},"sourceUrls":["https://en.wiktionary.org/wiki/ye"]},{"word":"ye","phonetics":[],"meanings":[{"partOfSpeech":"interjection","definitions":[{"definition":"Yes.","synonyms":[],"antonyms":[]}],"synonyms":[],"antonyms":[]}],"license":{"name":"CC BY-SA 3.0","url":"https://creativecommons.org/licenses/by-sa/3.0"},"sourceUrls":["https://en.wiktionary.org/wiki/ye"]}]}