{"word":"practically","rank":2466,"occurrence":0.0030323,"records":[{"word":"practically","phonetic":"/ˈpɹæktɪkli/","phonetics":[{"text":"/ˈpɹæktɪkli/","audio":"https://api.dictionaryapi.dev/media/pronunciations/en/practically-us.mp3","sourceUrl":"https://commons.wikimedia.org/w/index.php?curid=1749933","license":{"name":"BY-SA 3.0","url":"https://creativecommons.org/licenses/by-sa/3.0"}}],"meanings":[{"partOfSpeech":"adverb","definitions":[{"definition":"In practice; in effect. Not necessarily officially the case but what actually occurs.","synonyms":[],"antonyms":[]},{"definition":"Almost completely; almost entirely","synonyms":[],"antonyms":[],"example":"He was practically uneducated, barely able to read and write a simple sentence."},{"definition":"With respect to practices or a practice.","synonyms":[],"antonyms":[],"example":"He was practically educated and lacked theoretical depth."}],"synonyms":["all but"],"antonyms":["impractically"]}],"license":{"name":"CC BY-SA 3.0","url":"https://creativecommons.org/licenses/by-sa/3.0"},"sourceUrls":["https://en.wiktionary.org/wiki/practically"]}]}