{"word":"declination","rank":17769,"occurrence":0.0000564,"records":[{"word":"declination","phonetic":"/ˌdɛklɪˈneɪʃən/","phonetics":[{"text":"/ˌdɛklɪˈneɪʃən/","audio":"https://api.dictionaryapi.dev/media/pronunciations/en/declination-uk.mp3","sourceUrl":"https://commons.wikimedia.org/w/index.php?curid=89012592","license":{"name":"BY-SA 4.0","url":"https://creativecommons.org/licenses/by-sa/4.0"}}],"meanings":[{"partOfSpeech":"noun","definitions":[{"definition":"At a given point, the angle between magnetic north and true north.","synonyms":[],"antonyms":[]},{"definition":"At a given point, the angle between the line connecting this point with the geographical center of the earth and the equatorial plane.","synonyms":[],"antonyms":[]},{"definition":"A refusal.","synonyms":[],"antonyms":[]},{"definition":"(grammar) Declension.","synonyms":[],"antonyms":[]},{"definition":"The act or state of bending downward; inclination.","synonyms":[],"antonyms":[],"example":"declination of the head"},{"definition":"The act or state of falling off or declining from excellence or perfection; deterioration; decay; decline.","synonyms":[],"antonyms":[]},{"definition":"Deviation.","synonyms":[],"antonyms":[]}],"synonyms":[],"antonyms":[]}],"license":{"name":"CC BY-SA 3.0","url":"https://creativecommons.org/licenses/by-sa/3.0"},"sourceUrls":["https://en.wiktionary.org/wiki/declination"]}]}