{"word":"losers","rank":17000,"occurrence":0.000067,"records":[{"word":"losers","phonetics":[],"meanings":[{"partOfSpeech":"noun","definitions":[{"definition":"A person who loses; one who fails to win or thrive.","synonyms":[],"antonyms":["winner"],"example":"He was always a good loser."},{"definition":"Something of poor quality.","synonyms":[],"antonyms":[]},{"definition":"A person who is frequently unsuccessful in life.","synonyms":["failure"],"antonyms":[],"example":"I'm a constant loser in love."},{"definition":"A contemptible or unfashionable person.","synonyms":["crumb","losel","louse"],"antonyms":[]},{"definition":"One who or that which loses something, such as extra weight, car keys, etc.","synonyms":[],"antonyms":[]}],"synonyms":["crumb","losel","louse","failure"],"antonyms":["winner"]}],"license":{"name":"CC BY-SA 3.0","url":"https://creativecommons.org/licenses/by-sa/3.0"},"sourceUrls":["https://en.wiktionary.org/wiki/loser","https://en.wiktionary.org/wiki/losers"]}]}