{"word":"kissed","rank":1878,"occurrence":0.0041987,"records":[{"word":"kissed","phonetic":"/kɪst/","phonetics":[{"text":"/kɪst/","audio":"https://api.dictionaryapi.dev/media/pronunciations/en/kissed-us.mp3","sourceUrl":"https://commons.wikimedia.org/w/index.php?curid=1676792","license":{"name":"BY-SA 3.0","url":"https://creativecommons.org/licenses/by-sa/3.0"}}],"meanings":[{"partOfSpeech":"verb","definitions":[{"definition":"To touch with the lips or press the lips against, usually to show love or affection or passion, or as part of a greeting.","synonyms":[],"antonyms":[]},{"definition":"To (cause to) touch lightly or slightly; to come into contact.","synonyms":[],"antonyms":[],"example":"His ball kissed the black into the corner pocket."},{"definition":"Of two or more people, to touch each other's lips together, usually to express love or affection or passion.","synonyms":[],"antonyms":[]},{"definition":"To treat with fondness.","synonyms":[],"antonyms":[]}],"synonyms":[],"antonyms":[]}],"license":{"name":"CC BY-SA 3.0","url":"https://creativecommons.org/licenses/by-sa/3.0"},"sourceUrls":["https://en.wiktionary.org/wiki/kiss","https://en.wiktionary.org/wiki/kissed"]}]}