{"word":"stinging","rank":10450,"occurrence":0.0002868,"records":[{"word":"stinging","phonetic":"/ˈstɪŋɪŋ/","phonetics":[{"text":"/ˈstɪŋɪŋ/","audio":""}],"meanings":[{"partOfSpeech":"verb","definitions":[{"definition":"To hurt, usually by introducing poison or a sharp point, or both.","synonyms":[],"antonyms":[],"example":"Right so came out an adder of a little heathbush, and it stung a knight in the foot."},{"definition":"(of an insect) To bite.","synonyms":[],"antonyms":[]},{"definition":"(sometimes figurative) To hurt, to be in pain.","synonyms":[],"antonyms":[],"example":"My hand stings after knocking on the door so long."},{"definition":"To cause harm or pain to.","synonyms":[],"antonyms":[],"example":"I thought I could park in front of the hotel, but they stung me for five pounds!"}],"synonyms":[],"antonyms":[]},{"partOfSpeech":"noun","definitions":[{"definition":"The act by which someone receives a sting.","synonyms":[],"antonyms":[],"example":"stingings of remorse"}],"synonyms":[],"antonyms":[]},{"partOfSpeech":"adjective","definitions":[{"definition":"Having the capacity to sting.","synonyms":[],"antonyms":[],"example":"stinging nettles"},{"definition":"Precise and hurtful","synonyms":[],"antonyms":[]}],"synonyms":[],"antonyms":[]}],"license":{"name":"CC BY-SA 3.0","url":"https://creativecommons.org/licenses/by-sa/3.0"},"sourceUrls":["https://en.wiktionary.org/wiki/sting","https://en.wiktionary.org/wiki/stinging"]}]}