{"word":"fond","rank":1611,"occurrence":0.0049101,"records":[{"word":"fond","phonetic":"/fɒnd/","phonetics":[{"text":"/fɒnd/","audio":""},{"text":"/fɑnd/","audio":"https://api.dictionaryapi.dev/media/pronunciations/en/fond-us.mp3","sourceUrl":"https://commons.wikimedia.org/w/index.php?curid=1669310","license":{"name":"BY-SA 3.0","url":"https://creativecommons.org/licenses/by-sa/3.0"}}],"meanings":[{"partOfSpeech":"verb","definitions":[{"definition":"To have a foolish affection for, to be fond of.","synonyms":[],"antonyms":[]},{"definition":"To caress; to fondle.","synonyms":[],"antonyms":[]}],"synonyms":["grope","pet","touch up"],"antonyms":[]},{"partOfSpeech":"adjective","definitions":[{"definition":"(chiefly with of) Having a liking or affection (for).","synonyms":[],"antonyms":[]},{"definition":"Affectionate.","synonyms":[],"antonyms":[],"example":"a fond farewell"},{"definition":"Indulgent.","synonyms":[],"antonyms":[],"example":"I have fond grandparents who spoil me."},{"definition":"Outlandish; foolish; silly.","synonyms":[],"antonyms":[]},{"definition":"Foolish; simple; weak.","synonyms":[],"antonyms":[]},{"definition":"Doted on; regarded with affection.","synonyms":[],"antonyms":[]}],"synonyms":[],"antonyms":[]}],"license":{"name":"CC BY-SA 3.0","url":"https://creativecommons.org/licenses/by-sa/3.0"},"sourceUrls":["https://en.wiktionary.org/wiki/fond"]},{"word":"fond","phonetic":"/fɒnd/","phonetics":[{"text":"/fɒnd/","audio":""},{"text":"/fɑnd/","audio":"https://api.dictionaryapi.dev/media/pronunciations/en/fond-us.mp3","sourceUrl":"https://commons.wikimedia.org/w/index.php?curid=1669310","license":{"name":"BY-SA 3.0","url":"https://creativecommons.org/licenses/by-sa/3.0"}}],"meanings":[{"partOfSpeech":"noun","definitions":[{"definition":"The background design in lace-making.","synonyms":[],"antonyms":[]},{"definition":"Brown residue in pans from cooking meats and vegetables.","synonyms":[],"antonyms":[],"example":"He used the fond to make a classic French pan sauce."},{"definition":"A group of records having shared provenance.","synonyms":[],"antonyms":[]},{"definition":"Foundation; bottom; groundwork.","synonyms":[],"antonyms":[]},{"definition":"Fund, stock, or store.","synonyms":[],"antonyms":[]}],"synonyms":[],"antonyms":[]}],"license":{"name":"CC BY-SA 3.0","url":"https://creativecommons.org/licenses/by-sa/3.0"},"sourceUrls":["https://en.wiktionary.org/wiki/fond"]}]}