{"word":"producers","rank":13814,"occurrence":0.0001359,"records":[{"word":"producers","phonetics":[],"meanings":[{"partOfSpeech":"noun","definitions":[{"definition":"An individual or organization that creates goods and services.","synonyms":[],"antonyms":[]},{"definition":"One who produces an artistic production like a CD, a theater production, a film, a TV program and so on.","synonyms":[],"antonyms":[]},{"definition":"An organism that produces complex organic compounds from simple molecules and an external source of energy.","synonyms":[],"antonyms":[]},{"definition":"An arrest for speeding after which the driver is allowed seven days (or ten, in the Republic of Ireland) in which to produce his/her driving licence and related documents at a police station.","synonyms":[],"antonyms":[]},{"definition":"A furnace for producing combustible gas for fuel.","synonyms":[],"antonyms":[]}],"synonyms":[],"antonyms":[]}],"license":{"name":"CC BY-SA 3.0","url":"https://creativecommons.org/licenses/by-sa/3.0"},"sourceUrls":["https://en.wiktionary.org/wiki/producer","https://en.wiktionary.org/wiki/producers"]}]}