{"word":"producing","rank":4210,"occurrence":0.001542,"records":[{"word":"producing","phonetic":"/pɹəˈdjuːsɪŋ/","phonetics":[{"text":"/pɹəˈdjuːsɪŋ/","audio":""},{"text":"/pɹəˈdusɪŋ/","audio":"https://api.dictionaryapi.dev/media/pronunciations/en/producing-us.mp3","sourceUrl":"https://commons.wikimedia.org/w/index.php?curid=2707575","license":{"name":"BY-SA 3.0","url":"https://creativecommons.org/licenses/by-sa/3.0"}}],"meanings":[{"partOfSpeech":"verb","definitions":[{"definition":"To yield, make or manufacture; to generate.","synonyms":[],"antonyms":[]},{"definition":"To make (a thing) available to a person, an authority, etc.; to provide for inspection.","synonyms":[],"antonyms":[]},{"definition":"To sponsor and present (a motion picture, etc) to an audience or to the public.","synonyms":[],"antonyms":[]},{"definition":"To extend an area, or lengthen a line.","synonyms":[],"antonyms":[],"example":"to produce a side of a triangle"},{"definition":"To draw out; to extend; to lengthen or prolong.","synonyms":[],"antonyms":[],"example":"to produce a man's life to threescore"},{"definition":"To alter using technology, as opposed to simply performing.","synonyms":[],"antonyms":[],"example":"highly produced sound"}],"synonyms":["bring forth","come up with"],"antonyms":["destroy","ruin"]}],"license":{"name":"CC BY-SA 3.0","url":"https://creativecommons.org/licenses/by-sa/3.0"},"sourceUrls":["https://en.wiktionary.org/wiki/produce","https://en.wiktionary.org/wiki/producing"]}]}