{"word":"nickel","rank":12783,"occurrence":0.0001679,"records":[{"word":"nickel","phonetic":"/ˈnɪk.əl/","phonetics":[{"text":"/ˈnɪk.əl/","audio":"https://api.dictionaryapi.dev/media/pronunciations/en/nickel-us.mp3","sourceUrl":"https://commons.wikimedia.org/w/index.php?curid=1755181","license":{"name":"BY-SA 3.0","url":"https://creativecommons.org/licenses/by-sa/3.0"}}],"meanings":[{"partOfSpeech":"noun","definitions":[{"definition":"A silvery elemental metal with an atomic number of 28 and symbol Ni.","synonyms":[],"antonyms":[]},{"definition":"A coin worth 5 cents.","synonyms":[],"antonyms":[]},{"definition":"(by extension) Five dollars.","synonyms":[],"antonyms":[]},{"definition":"(by extension) Five hundred dollars.","synonyms":[],"antonyms":[]},{"definition":"(sometimes the nickel or the hot nickel) Interstate 5, a highway that runs along the west coast of the United States.","synonyms":[],"antonyms":[]},{"definition":"A playing card with the rank of five","synonyms":[],"antonyms":[]},{"definition":"A five-year prison sentence.","synonyms":[],"antonyms":[]},{"definition":"A defensive formation with five defensive backs, one of whom is a nickelback, instead of the more common four.","synonyms":[],"antonyms":[]}],"synonyms":[],"antonyms":[]},{"partOfSpeech":"verb","definitions":[{"definition":"To plate with nickel.","synonyms":[],"antonyms":[]}],"synonyms":[],"antonyms":[]}],"license":{"name":"CC BY-SA 3.0","url":"https://creativecommons.org/licenses/by-sa/3.0"},"sourceUrls":["https://en.wiktionary.org/wiki/nickel"]}]}