{"word":"sonorous","rank":9993,"occurrence":0.0003236,"records":[{"word":"sonorous","phonetic":"/ˈsɒn.əɹ.əs/","phonetics":[{"text":"/ˈsɒn.əɹ.əs/","audio":""},{"text":"/ˈsoʊ.nə.ɹəs/","audio":"https://api.dictionaryapi.dev/media/pronunciations/en/sonorous-us.mp3","sourceUrl":"https://commons.wikimedia.org/w/index.php?curid=1637684","license":{"name":"BY-SA 3.0","url":"https://creativecommons.org/licenses/by-sa/3.0"}}],"meanings":[{"partOfSpeech":"adjective","definitions":[{"definition":"Capable of giving out a deep, resonant sound.","synonyms":[],"antonyms":[],"example":"The highlight of the hike was the sonorous cave, which produced a ringing echo from the hiker’s shouts."},{"definition":"Full of sound and rich, as in language or verse.","synonyms":[],"antonyms":[],"example":"He was selected to give the opening speech thanks to his imposing, sonorous voice."},{"definition":"Wordy or grandiloquent.","synonyms":[],"antonyms":[]},{"definition":"Produced with a relatively open vocal tract and relatively little obstruction of airflow.","synonyms":[],"antonyms":[]}],"synonyms":["booming","canorous","prolix","sesquipedalian","sonoral"],"antonyms":[]}],"license":{"name":"CC BY-SA 3.0","url":"https://creativecommons.org/licenses/by-sa/3.0"},"sourceUrls":["https://en.wiktionary.org/wiki/sonorous"]}]}