{"word":"tennis","rank":9656,"occurrence":0.0003529,"records":[{"word":"tennis","phonetic":"/ˈtɛn.ɪs/","phonetics":[{"text":"/ˈtɛn.ɪs/","audio":""}],"meanings":[{"partOfSpeech":"noun","definitions":[{"definition":"A sport played by two players (or four in doubles), who alternately strike the ball over a net using racquets.","synonyms":[],"antonyms":[]},{"definition":"A match in this sport.","synonyms":[],"antonyms":[]},{"definition":"An earlier game in which a ball is driven to and fro, or kept in motion by striking it with a racquet or with the open hand.","synonyms":[],"antonyms":[]}],"synonyms":[],"antonyms":[]},{"partOfSpeech":"verb","definitions":[{"definition":"To play tennis.","synonyms":[],"antonyms":[]},{"definition":"To drive backward and forward like a tennis ball.","synonyms":[],"antonyms":[]}],"synonyms":[],"antonyms":[]}],"license":{"name":"CC BY-SA 3.0","url":"https://creativecommons.org/licenses/by-sa/3.0"},"sourceUrls":["https://en.wiktionary.org/wiki/tennis"]}]}