{"word":"malignant","rank":7689,"occurrence":0.0005935,"records":[{"word":"malignant","phonetic":"/məˈlɪɡnənt/","phonetics":[{"text":"/məˈlɪɡnənt/","audio":"https://api.dictionaryapi.dev/media/pronunciations/en/malignant-us.mp3","sourceUrl":"https://commons.wikimedia.org/w/index.php?curid=827790","license":{"name":"BY-SA 3.0","url":"https://creativecommons.org/licenses/by-sa/3.0"}}],"meanings":[{"partOfSpeech":"noun","definitions":[{"definition":"A deviant; a person who is hostile or destructive to society.","synonyms":[],"antonyms":[]},{"definition":"A person who fought for Charles I in the English Civil War.","synonyms":[],"antonyms":[]}],"synonyms":[],"antonyms":[]},{"partOfSpeech":"adjective","definitions":[{"definition":"Harmful, malevolent, injurious.","synonyms":[],"antonyms":[],"example":"malignant temper;  malignant revenge;  malignant infection"},{"definition":"Tending to produce death; threatening a fatal issue.","synonyms":[],"antonyms":[],"example":"a malignant tumor"}],"synonyms":[],"antonyms":["benign","non-malignant"]}],"license":{"name":"CC BY-SA 3.0","url":"https://creativecommons.org/licenses/by-sa/3.0"},"sourceUrls":["https://en.wiktionary.org/wiki/malignant"]}]}